Workbook

Sheet Read Me
B2: AI-RedForge — Blueprint & Execution Plan
B3: Amdocs Agentic AI Red-Team Factory · v1.1 · Sep 2026 (v1.1 Sep 10: +Console UI, +Exec Milestones, +Context Memory) · Offering #1 — Agentic Assurance Suite flagship
B5: Why This Wins
B6: 1. Framework: AI-RedForge — continuous adversarial testing of LLM apps, copilots and agents against OWASP LLM + Agentic Top 10.
B7: 2. Market hook: ~$2.3B (2026) growing ~28% CAGR; EU AI Act in force since Aug 2026 — procurement now demands AI-security evidence.
B8: 3. Differentiator: canary-proven exfiltration, dual-mode judging, bounded mutation rounds, audit-grade regulatory dossier.
B9: 4. Pairs with offering #2 (MCP/agent supply-chain assurance) as the Agentic Assurance Suite land-grab.
B10: 5. Critical path: 12-week build > internal PoC wk10 > lighthouse CSP copilot beta wk12.
B12: How to Use
B13: 1. This workbook is the execution instrument for AI-RedForge — the Agentic AI Red-Team Factory blueprint.
B14: 2. Blue cells are editable inputs: scorecard weights/actuals, KPI actuals, risk ratings, task status/%.
B15: 3. Build Plan: status dropdown per task + live 12-week Gantt rendering from Start/End weeks.
... B23: Workbook Map
B24: Sheet | C24: Contents
B25: Architecture | C25: 6 layers L0-L5 + 7 design tenets
B26: Target Catalogue | C26: 10 target classes with interfaces, packs, prod-safety notes
B27: Technique Catalog | C27: 40 attack techniques mapped to OWASP LLM/Agentic Top 10 + tools + gate levels
B28: Scoring Model | C28: Live AI Security Scorecard calculator
B29: Delivery Workflow | C29: Phases A0-A6 with gates, inputs, outputs, owners
B30: Swarm DAG | C30: 15-node execution graph + 14-artifact edge manifest
B31: Agent Roster | C31: 14 agents: mission, tools, guardrails, autonomy
B32: MCP Integration | C32: 13 tool servers with priorities and estimates
B33: Console UI | C33: v1.1 — Dual-mode RedForge Console: 10 screens, HUD/JARVIS layer, stack & personas
B34: Build Plan | C34: 38 tasks (v1.1: T23 split into T23a/b/c), owners, dependencies, live 12-week Gantt
B35: Exec Milestones | C35: v1.1 — Demo execution plan M0-M6c with acceptance gates + live status
... B40: Sources | C40: Reference base + disclaimer
B43: Technique Coverage by OWASP Category (40-technique catalog v1)
B44: Category | C44: Techniques
B45: Injection (PIN) | C45: 10
B46: Disclosure (EXF) | C46: 7
B47: Output (OUT) | C47: 4
B48: Agency (AGE) | C48: 7
B49: Memory (MEM) | C49: 3
B50: Consumption (CON) | C50: 4
B51: Misinformation (HAL) | C51: 3
B52: Supply chain (SUP) | C52: 2

Sheet Architecture
B2: Architecture — Six Layers & Design Tenets
B4: Layer | C4: Name | D4: Responsibility | E4: Key Tech | F4: Build vs Assemble
B5: L0 | C5: Target interface & collection | D5: Connect to every target class read/write as an attacker would: model APIs, agent endpoints, MCP tool schemas, chat UIs, RAG corpora samples | E5: OpenAI-compatible adapters, agent/MCP introspection, browser automation, gateway logs | F5: Assemble (wrappers)
B6: L1 | C6: Threat & attack knowledge model | D6: Technique library mapped to OWASP LLM Top 10 (2025) + Agentic Top 10 (2026) + MITRE ATLAS; payload corpus; target catalogue | E6: 40-technique catalog v1, payload seeds, persona library | F6: Build — core IP
B7: L2 | C7: Attack engine | D7: Attack generation (mutation, multi-turn strategy), campaign execution, sandboxing, dual-mode judging | E7: PyRIT pipelines, Garak probes, promptfoo suites, Giskard scans, judge framework | F7: Build — core IP
B8: L3 | C8: Agentic orchestration | D8: Campaign planning, parallel red operators, bounded mutation rounds, human gates | E8: LangGraph, MCP tool-servers, Postgres checkpointer | F8: Build — differentiator
B9: L4 | C9: Evidence, scoring & reporting | D9: Findings schema, AI Security Scorecard, regulatory dossier (EU AI Act Art 15 / ISO 42001), report generation | E9: Postgres + object store, OPA, citation-linted reports | F9: Build (light)
B10: L5 | C10: Delivery plane | D10: Client portal, CI/CD gate on model & guardrail releases, continuous regression mode | E10: Hub portal tooling, CI gate, REST | F10: Assemble
B13: Design Tenets (invariants enforced in code review)
B14: # | C14: Tenet
B15: T1 | C15: Attack the system, not the vendor demo: test the deployed app + guardrails + tools end-to-end, never a bare model endpoint.
B16: T2 | C16: Dual-mode judging: rule-based detectors first, LLM-as-judge second, human confirmation for criticals — no single-judge verdicts.
B17: T3 | C17: Bounded campaign rounds: operator>judge>mutator loop capped at 3 rounds with diminishing-returns cutoff — evolution, not endless fuzzing.
B18: T4 | C18: No real data out: exfiltration proven via canaries and honeytokens only; real PII never leaves the target boundary.
B19: T5 | C19: Production attacks and side-effect-capable tool actions only behind Gatekeeper approval (ROAI = rules of AI engagement).
B20: T6 | C20: Single-writer rule: only Judge marks success-candidates, only Verifier confirms findings, only OPA derives severity.
B21: T7 | C21: Every finding ships with full transcript evidence + judge confidence + human-confirmed flag — audit-grade by construction.

Sheet Target Catalogue
B2: Target Asset Catalogue — 10 Target Classes
B4: # | C4: Target Class | D4: Examples | E4: Interface (L0) | F4: Attack Packs | G4: Special Risks | H4: Prod-Safety Notes
B5: 1 | C5: Customer-facing chatbot / care bot | D5: CSP care copilot, sales assistant | E5: Model API + chat UI (browser) | F5: PIN, EXF, OUT, HAL | G5: Brand damage, regulated answers (billing/tariffs) | H5: Prod testing rate-capped; G1 for content-safety packs
B6: 2 | C6: Employee copilot | D6: M365-style assistant over intranet | E6: Agent endpoint + MCP tool schemas | F6: PIN, EXF, AGE, MEM | G6: Internal data sprawl, tool abuse | H6: Canary-seeded intranet docs
B7: 3 | C7: RAG knowledge app | D7: Policy/KB search assistant | E7: RAG API + corpus sample | F7: PIN-004, EXF, MEM | G7: Corpus poisoning, cross-tenant leakage | H7: Staging corpus with canaries first
B8: 4 | C8: Tool-calling agent | D8: Ticketing/CRM agent with tools | E8: Agent endpoint + tool ACL dump | F8: PIN, AGE, CON | G8: Destructive actions, privilege chains | H8: Sandbox tenant with simulated tools
B9: 5 | C9: Multi-agent workflow (A2A) | D9: Orchestrator + worker agents | E9: Gateway + agent registry | F9: PIN, AGE-006, MEM | G9: A2A instruction forgery, cascading misuse | H9: Isolated workflow replica
B10: 6 | C10: Coding assistant | D10: Internal code-gen copilot | E10: IDE plugin API + repo context | F10: PIN, OUT-002/003, SUP | G10: Generated-code injection into pipelines | H10: Fork sandbox repo only
B11: 7 | C11: Voice AI agent | D11: IVR replacement, voice support | E11: Voice endpoint + transcripts | F11: PIN (audio), EXF, HAL | G11: Voice-phishing of the agent, data readback | H11: Synthetic voice, test numbers only
B12: 8 | C12: AI gateway / firewall | D12: Guardrail layer in front of models | E12: Gateway config + bypass probes | F12: PIN (bypass), CON | G12: False sense of security; bypass economics | H12: Bypass proven with benign probes + canary payload
B13: 9 | C13: Fine-tuned / proprietary model endpoint | D13: Custom CSP model | E13: Inference API | F13: EXF-004, HAL, CON | G13: Memorized data extraction | H13: Quota-budgeted; extraction via canaries
B14: 10 | C14: Agentic process automation | D14: AI-driven RPA over BSS/OSS | E14: Automation API + role mappings | F14: PIN, AGE, MEM | G14: Fraud-enabling actions on telco systems | H14: Shadow tenant; never production BSS writes
B16: Cross-sell: classes 4, 5, 10 expose tool/MCP surfaces — hand off to offering #2 (agent & MCP supply-chain assurance) for the inventory/gate half.

Sheet Technique Catalog
B2: Attack Technique Catalog v1 — 40 Techniques
B4: Technique ID | C4: OWASP Category | D4: Technique | E4: OWASP Ref | F4: Primary Tool | G4: Gate Level
B5: PIN-001 | C5: Prompt Injection (LLM01) | D5: Direct instruction override | E5: LLM01:2025 | F5: PyRIT orchestrator | G5: Safe
B6: PIN-002 | C6: Prompt Injection (LLM01) | D6: Role/persona hijack (DAN-style) | E6: LLM01:2025 | F6: Garak(dan,lemma) | G6: Safe
B7: PIN-003 | C7: Prompt Injection (LLM01) | D7: System-prompt extraction via injection | E7: LLM01+07 | F7: promptfoo redteam | G7: Safe
B8: PIN-004 | C8: Prompt Injection (LLM01) | D8: Indirect injection via retrieved RAG document | E8: LLM01:2025 | F8: PyRIT + canary docs | G8: Sensitive
B9: PIN-005 | C9: Prompt Injection (LLM01) | D9: Indirect injection via tool/web content (agentic browsing) | E9: LLM01+Agentic | F9: PyRIT + web canary | G9: Sensitive
B10: PIN-006 | C10: Prompt Injection (LLM01) | D10: Multi-turn context erosion (gradual reframing) | E10: LLM01:2025 | F10: PyRIT multi-turn | G10: Safe
B11: PIN-007 | C11: Prompt Injection (LLM01) | D11: Encoded/obfuscated payload (base64/leetspeak/unicode) | E11: LLM01:2025 | F11: Garak encoding probes | G11: Safe
B12: PIN-008 | C12: Prompt Injection (LLM01) | D12: Payload smuggling via structured data (JSON/markdown/code) | E12: LLM01:2025 | F12: promptfoo | G12: Safe
B13: PIN-009 | C13: Prompt Injection (LLM01) | D13: Language-switch bypass (low-resource language) | E13: LLM01:2025 | F13: Garak lang probes | G13: Safe
B14: PIN-010 | C14: Prompt Injection (LLM01) | D14: Template/copy-paste injection (help-me-debug framing) | E14: LLM01:2025 | F14: PyRIT persona | G14: Safe
B15: EXF-001 | C15: Sensitive Disclosure (LLM02/07) | D15: System prompt leakage via direct ask | E15: LLM07:2025 | F15: Garak leakrepl | G15: Safe
... B44: SUP-002 | C44: Supply Chain (LLM03) | D44: Agent permission sprawl precheck (cross-ref #2) | E44: LLM03+Agentic | F44: Registry diff | G44: Safe
B46: Gate levels: Safe = standard packs; Sensitive = G1 two-person approval + sandbox-first; 'G1 + budget' = consumption packs with hard cost caps. Severity derived by OPA from judge confidence + asset criticality.

Sheet Scoring Model
B2: AI Security Scorecard — Live Calculator (edit blue cells)
B4: Dimensions, weights and engagement actuals
B5: Dimension | C5: Weight | D5: Metric Definition | E5: Actual % (0-100) | F5: Weighted Contribution
B6: Injection Resistance | C6: 0.25 | D6: % injection attempts neutralized (PIN pack) | E6: 44 | F6: =E6*$C6 -> 11
B7: Data Protection | C7: 0.2 | D7: % disclosure attempts blocked (EXF pack incl. canaries) | E7: 55 | F7: =E7*$C7 -> 11
B8: Agency & Tool Control | C8: 0.2 | D8: % agency abuse paths closed (AGE pack) | E8: 40 | F8: =E8*$C8 -> 8
B9: Output Safety | C9: 0.15 | D9: % output-handling flaws closed (OUT pack) | E9: 50 | F9: =E9*$C9 -> 7.5
B10: Availability & Cost Resilience | C10: 0.1 | D10: % consumption attacks within budget caps (CON pack) | E10: 60 | F10: =E10*$C10 -> 6
B11: Regulatory Evidence Readiness | C11: 0.1 | D11: % findings mapped to EU AI Act/ISO controls with evidence | E11: 30 | F11: =E11*$C11 -> 3
B12: Total (weights must equal 100%) | C12: =SUM(C6:C11) -> 1 | D12: =IF(ROUND(C12,4)=1,"OK — weights total 100%","ADJUST — weights do not total 100%") -> OK — weights total 100%
B14: Results (live)
B15: AI Security Score (0-100) | F15: =ROUND(SUM(F6:F11),1) -> 46.5
B16: Band | F16: =IF(F15>=80,"Good",IF(F15>=60,"Fair",IF(F15>=40,"Poor","Critical"))) -> Poor
B17: Maturity level | F17: =IF(F15>=80,"Level 4-5 (Optimizing)",IF(F15>=60,"Level 3 (Defined)",IF(F15>=40,"Level 2 (Managed)","Level 1 (Initial)"))) -> Level 2 (Managed)
B19: Sample baseline actuals pre-filled — replace with campaign measurements per attack pack.
B20: Bands: <40 Critical / 40-59 Poor / 60-79 Fair / >=80 Good. Scorecard feeds the EU AI Act Art 15 robustness dossier.

Sheet Delivery Workflow
B2: Delivery Workflow — Phases, Gates, Owners
B4: Phase | C4: Name | D4: Timing | E4: Key Activities | F4: Client Inputs | G4: Outputs | H4: Gate to Exit | I4: Owner
B5: A0 | C5: Readiness & ROAI | D5: Week 1 | E5: Scope targets + safety boundaries, sign Rules of AI Engagement, seed canaries/honeytokens, budget caps | F5: Target inventory, prod-change calendar, tool ACLs | G5: ROAI pack, canary manifest, budget caps | H5: ROAI signed; canary seeding verified; sandbox tenant ready | I5: Engagement Lead
B6: A1 | C6: Recon & Surface Mapping | D6: Week 1-2 | E6: Endpoint/tool/RAG inventory, guardrail fingerprinting, system-prompt harvesting (passive), shadow-tool diff | F6: API keys, agent registry access | G6: Target surface map (A2), guardrail fingerprint | H6: All scoped targets mapped; fingerprint reproducible | I6: AI Sec Engineer
B7: A2 | C7: Baseline & Quick Wins | D7: Week 2 | E7: Refusal-rate baseline, benign-bypass baseline, first PIN/EXF sweep, 72h quick-win report | F7: Surface map | G7: Baseline metrics + quick-win findings | H7: Quick-win report delivered <=72h after A1 exit | I7: Red Operator Pod
B8: A3 | C8: Campaign Rounds 1-3 | D8: Week 3-4 | E8: Technique packs per target class; parallel red operators; judge verdicts; bounded payload mutation | F8: Baselines, technique packs | G8: Candidate findings + evolved payload corpus | H8: Round-3 marginal-gain < threshold; coverage = packs executed / packs planned | I8: Red Operator Pod
B9: A4 | C9: Chain Building & Deep Exploitation | D9: Week 4-5 | E9: Combine confirmed weaknesses into kill chains (injection>agency>exfil); business-impact validation in sandbox | F9: Confirmed findings | G9: Kill-chain PoCs with impact narrative | H9: Every critical chain reproduced or downgraded with reason | I9: Chain-Builder + Red Lead
B10: A5 | C10: Report & Regulatory Dossier | D10: Week 5-6 | E10: AI Security Scorecard, EU AI Act Art 15 robustness evidence, ISO 42001 annex, remediation playbook | F10: Verified findings, chain PoCs | G10: Report v1 + regulatory dossier + 90-day plan | H10: Client sign-off; guardrail-tuning plan agreed | I10: Engagement Lead
B11: A6 | C11: Continuous Mode | D11: Monthly | E11: Regression on model/guardrail/prompt updates, monthly threat-intel technique packs, drift scorecard | F11: Subscription active | G11: Regression results + updated scorecard | H11: No critical regression unreported >24h | I11: Sentinel Pod
B13: Packaging: Assess (A0-A5, $50-150K band) / Continuous (A6, $20-50K/mo) / Regulatory-evidence retainer (AI Act Art 15). Pairs with offering #2 as Agentic Assurance Suite.

Sheet Swarm DAG
B2: Swarm Execution DAG — Nodes & Edge Manifest
B4: Node contracts (bounded mutation rounds keep the graph acyclic per campaign epoch)
B5: Node | C5: Role | D5: Type | E5: Phase / Timing | F5: Output Artifact | G5: Input | H5: Validation Gate | I5: On Failure | J5: Critical Path
B6: N0 | C6: Mission Control (campaign planner) | D6: Agent | E6: A0 / wk1 | F6: A1 campaign plan + ROAI manifest | G6: scope, targets, budgets | H6: ROAI signed; plan schema valid | I6: Halt — no workarounds | J6: Yes
B7: N1 | C7: Recon Agent | D7: Agent | E7: A1 / wk1-2 | F7: A2 target surface map + guardrail fingerprint | G7: API keys, registry access | H7: All scoped targets enumerated; fingerprint reproducible | I7: Retry read-only; flag target partial | J7: Yes
B8: N2 | C8: Attack Strategist | D8: Agent | E8: A2 / wk2 | F8: A3 technique-pack assignments + seed payloads | G8: surface map, technique catalog | H8: Pack-target matrix approved by red lead | I8: Fall back to standard pack set | J8: Yes
B9: N3 | C9: Red Operators (multi-instance, rounds 1-3) | D9: Agent | E9: A3 / wk3-4 | F9: A4 attack transcripts + candidate events | G9: packs, seeds, budget caps | H9: Rate caps enforced; payload safety screen passed | I9: Kill instance, log, reschedule | J9: Yes (CP)
B10: N4 | C10: Judge (rule-first, LLM-second) | D10: Agent | E10: A3 / wk3-4 | F10: A5 verdicts (success/fail/close + confidence) | G10: transcripts + detectors | H10: Dual-mode agreement; disagreement escalated to human | I10: Mark unverifiable; queue human triage | J10: Yes (CP)
B11: N5 | C11: Mutator (bounded evolution) | D11: Agent | E11: A3 / wk3-4 | F11: A6 evolved payload set (rounds 2-3) | G11: close-but-failed transcripts | H11: Max 3 rounds; marginal-gain cutoff | I11: Stop evolution, proceed with confirmed set | J11: Yes
B12: N6 | C12: Chain-Builder | D12: Agent | E12: A4 / wk4-5 | F12: A7 kill-chain proposals | G12: confirmed findings + topology | H12: Every chain step individually evidenced | I12: Chain split into single findings | J12: Yes
B13: G1 | C13: Gatekeeper — sensitive actions | D13: Human gate | E13: A3/A4 | F13: A7' approvals log (prod attacks, tool actions, budgets) | G13: sensitive-pack request | H13: Two-person rule; ROAI scope + budget match | I13: Deny > run sandbox variant | J13: Yes
B14: N7 | C14: Verifier (human-grade reproduction) | D14: Agent | E14: A4 / wk5 | F14: A8 confirmed findings register | G14: candidates + chains | H14: Reproduced from transcripts; false positives voided | I14: Void finding; FP-rate KPI updated | J14: Yes (CP)
B15: N8 | C15: Scorer | D15: Agent | E15: A5 / wk5 | F15: A9 AI Security Scorecard | G15: confirmed register + baselines | H15: OPA-only derivation; per-pack math shown | I15: Flag dimension incomplete | J15: No
B16: N9 | C16: Compliance Mapper | D16: Agent | E16: A5 / wk5 | F16: A10 EU AI Act / ISO dossier | G16: confirmed register | H16: Every finding >=1 control ref (Art 15.2 robustness, ISO A.10.2, NIST AI RMF) | I16: Block report (hard dependency) | J16: No
... B20: N12 | C20: Sentinel (continuous) | D20: Agent | E20: A6 / monthly | F20: A13 regression deltas + updated scorecard | G20: updates feed, new packs | H20: Update detection within 24h; regression retest automatic | I20: Skip cycle, alert ops | J20: No
B23: Edge manifest — artifact contracts
B24: ID | C24: Artifact | D24: Producer > Consumer | E24: Contract / Validation at Edge
B25: A1 | C25: Campaign plan + ROAI manifest | D25: N0 > all | E25: ROAI signed; budgets capped; canary manifest verified
B26: A2 | C26: Target surface map + guardrail fingerprint | D26: N1 > N2, N3, N12 | E26: All scoped targets enumerated; fingerprint reproducible
B27: A3 | C27: Technique-pack assignments + seed payloads | D27: N2 > N3 | E27: Pack-target matrix approved; payload safety screen passed
B28: A4 | C28: Attack transcripts + candidate events | D28: N3 > N4 | E28: Full transcript stored; token/cost metering attached
B29: A5 | C29: Judge verdicts (confidence-scored) | D29: N4 > N5 (close), N6/N7 (success) | E29: Dual-mode agreement or human escalation
B30: A6 | C30: Evolved payload set | D30: N5 > N3 (rounds 2-3) | E30: Bounded: max 3 rounds; marginal-gain cutoff enforced
B31: A7 | C31: Kill-chain proposals | D31: N6 > G1 | E31: Each step individually evidenced; impact narrative stated
B32: A7' | C32: Approvals log | D32: G1 > N3, N7 | E32: Two-person signature; budget + scope match
B33: A8 | C33: Confirmed findings register | D33: N7 > N8, N9, N10, N11, N12 | E33: Reproduced from transcripts; FP-voided; human-confirmed flag for criticals
B34: A9 | C34: AI Security Scorecard | D34: N8 > N11 | E34: OPA-derived; per-pack math attached
B35: A10 | C35: Regulatory dossier | D35: N9 > N11 | E35: Every finding mapped (EU AI Act Art 15, ISO 42001, NIST AI RMF)
... B38: A13 | C38: Regression deltas + scorecard | D38: N12 > client + epoch N+1 | E38: Update detected <24h; retest queue auto-created
B40: Critical path: N0 > N1 > N2 > N3(R1) > N4 > N7 > N11 > G2. Mutation rounds R2/R3 run off-path; pull G1 board early for sensitive packs.

Sheet Agent Roster
B2: Agent Roster — 14 Agents
B4: Agent | C4: Node | D4: Mission | E4: MCP Tools | F4: Writes | G4: Guardrails | H4: Autonomy
B5: Mission Control | C5: N0 | D5: Plan campaigns, enforce ROAI/budgets, track SLAs | E5: all (metadata) | F5: campaign plan | G5: Cannot skip gates; budgets hard-capped | H5: L1+
B6: Recon Agent | C6: N1 | D6: Map targets, fingerprint guardrails, find shadow tools | E6: target-adapter, browser, registry | F6: surface map | G6: Read-only unless G1-approved | H6: L1
B7: Attack Strategist | C7: N2 | D7: Select technique packs, craft seeds, plan rounds | E7: technique catalog, pyrit | F7: pack assignments | G7: Human red-lead approval of matrix | H7: L1
B8: Red Operator (xN) | C8: N3 | D8: Execute multi-turn attacks across packs | E8: pyrit, garak, promptfoo, browser | F8: transcripts + candidates | G8: Rate caps; payload safety screen; sandbox-first | H8: L1
B9: Judge | C9: N4 | D9: Verdict success/fail/close with confidence | E9: mcp-judge, detectors | F9: verdicts | G9: Rule-first, LLM-second; disagreement > human | H9: L1
B10: Mutator | C10: N5 | D10: Evolve close-but-failed payloads | E10: pyrit memory, llm-gateway | F10: evolved payloads | G10: Bounded 3 rounds; no real-data payloads | H10: L1
B11: Chain-Builder | C11: N6 | D11: Assemble kill chains from confirmed weaknesses | E11: evidence, topology map | F11: chain proposals | G11: Each step individually evidenced | H11: L1
B12: Gatekeeper | C12: G1/G2 | D12: Approve sensitive actions and report release | E12: - | F12: approvals log | G12: Two-person rule via interrupt() | H12: Human
B13: Verifier | C13: N7 | D13: Reproduce findings; kill false positives | E13: targeted replays | F13: confirmed register | G13: Only node allowed to confirm | H13: L1
B14: Scorer | C14: N8 | D14: Compute AI Security Scorecard | E14: opa | F14: scorecard | G14: OPA-only derivation | H14: L1
B15: Compliance Mapper | C15: N9 | D15: Map findings to EU AI Act / ISO / NIST AI RMF | E15: opa mapping tables | F15: dossier | G15: Versioned mappings | H15: L1
... B18: Sentinel | C18: N12 | D18: Regression on updates; deploy monthly threat-intel packs | E18: all collectors | F18: deltas + scorecard | G18: 24h update detection; delta-scoped retests | H18: L2
B20: Autonomy: L0 approve-every-step (first 2 engagements) / L1 gates-only (default) / L2 autonomous Safe packs in continuous mode / L3 scoped Sensitive with sampling audit (after 10 clean L2 runs).

Sheet MCP Integration
B2: MCP Tool-Server Build List — 13 Servers
B4: Server | C4: Wraps | D4: Exposed Tools (examples) | E4: Build Priority | F4: Est. Weeks | G4: Type
B5: mcp-target-adapter | C5: OpenAI-compatible + agent APIs | D5: chat, tool_call, list_tools, health | E5: P0 | F5: 2 | G5: Core
B6: mcp-pyrit | C6: Microsoft PyRIT | D6: run_pipeline, memory_query, score | E6: P0 | F6: 2 | G6: Core
B7: mcp-garak | C7: NVIDIA Garak | D7: run_probe, list_probes, report | E7: P1 | F7: 1 | G7: Core
B8: mcp-promptfoo | C8: promptfoo redteam | D8: run_suite, assertions, regression_diff | E8: P1 | F8: 1 | G8: Core
B9: mcp-giskard | C9: Giskard scanner | D9: scan, report_insights | E9: P2 | F9: 1 | G9: Core
B10: mcp-browser | C10: Browser automation | D10: open_chat, send, screenshot, read_reply | E10: P1 | F10: 2 | G10: Core
B11: mcp-judge | C11: Rule detectors + LLM-as-judge | D11: rule_check, llm_judge, combine_verdict | E11: P0 | F11: 2 | G11: Core
B12: mcp-canary | C12: Canary/honeytoken mgmt | D12: seed_corpus, make_webhook, check_hits | E12: P0 | F12: 1 | G12: Core
B13: mcp-opa | C13: OPA/Rego | D13: evaluate_severity, gate_check, score_dimensions | E13: P0 | F13: 1 | G13: Core
B14: mcp-evidence | C14: Postgres + S3 | D14: store(transcript, finding), link | E14: P0 | F14: 1 | G14: Core
B15: mcp-llm-gateway | C15: Target model access mgmt | D15: call_model, usage, budget_enforce | E15: P1 | F15: 1 | G15: Core
... B17: mcp-calypsoai | C17: CalypsoAI (optional) | D17: scan_target, report | E17: P2 | F17: 1 | G17: Optional
B19: Discipline: JSON-schema typed I/O, budget metering on every target call, payload safety screen before dispatch, contract tests in CI.

Sheet Console UI
B2: RedForge Console — Dual-Mode Agentic UI (Ops + HUD/JARVIS, D7)
B4: Dual-mode architecture — one engine, two skins over one event stream
B5: Mode | C5: Role | D5: Characteristics | E5: Screens
B6: Ops Mode (default) | C6: Audit-grade daily driver | D6: Dense, keyboard-first, WCAG 2.1 AA, printable for auditors; schematic React Flow DAG; for operators & audit reviews | E6: All 10 screens
B7: HUD Mode (JARVIS layer) | C7: Cinematic command center | D7: 3D swarm constellation, voice I/O, shader HUD (bloom/scanlines/glass), briefings, time-travel replay; for war-room walls, exec demos, sales | E7: Command Center, Mission Control, Scorecard, Sentinel, Gatekeeper
B10: Screens (10)
B11: # | C11: Screen | D11: Contents | E11: Modes | F11: Primary Data Source
B12: 1 | C12: Command Center | D12: Active campaigns, swarm health, budget burn, KPI tiles | E12: Both | F12: campaign plan + KPIs
B13: 2 | C13: Mission Control (flagship) | D13: Live 15-node DAG, streaming transcripts, R1-R3 round tracker, budget meters, kill-switch, agent-trace replay | E13: Both (3D in HUD) | F13: DAG events + transcripts
B14: 3 | C14: Findings Explorer | D14: Filters pack/technique/severity/target; evidence drawer (transcript + dual-mode verdict + confidence); FP-void workflow; kill-chain graph | E14: Ops-first | F14: findings register + evidence store
B15: 4 | C15: AI Security Scorecard | D15: Live 6-dimension radar, weight sliders (mirrors this workbook), trend lines, band transitions | E15: Both | F15: scorecard engine (OPA)
B16: 5 | C16: Regulatory Dossier | D16: EU AI Act Art 15 / ISO 42001 / NIST AI RMF matrix, evidence-linked controls, PDF export | E16: Ops | F16: compliance mapping
B17: 6 | C17: Gatekeeper Console | D17: G1/G2 approval inbox, two-person rule, ROAI scope check, approvals log (audible alerts in HUD) | E17: Both | F17: gate events + approvals log
B18: 7 | C18: Target Registry | D18: 10 target classes: health, surface maps, canary status | E18: Ops | F18: target catalogue + recon
B19: 8 | C19: Technique Library | D19: 40 techniques, payload corpus manager, mutation lineage visualizer | E19: Ops | F19: technique catalog + corpus
B20: 9 | C20: Sentinel / Continuous | D20: Regression timeline, update detections, drift scorecard, CI-gate widget | E20: Both | F20: sentinel deltas
B21: 10 | C21: Admin & Governance | D21: RBAC/SSO, audit-trail viewer, MCP server status board, budget caps | E21: Ops | F21: governance config
B24: HUD Mode components (JARVIS layer)
B25: Component | C25: Tech | D25: What it does
B26: 3D swarm constellation | C26: react-three-fiber + drei | D26: 15 agent nodes as glowing orbs; particle flows along attack paths (chains light up as they execute); camera fly-to; exploded agent views; auto-degrade to schematic DAG on weak GPU
B27: Core orb (swarm identity) | C27: R3F + bloom postprocessing | D27: Central pulsing identity: idle breathing, attack strobe, red gate-alert sweep
B28: Shader HUD chrome | C28: WebGL postprocessing | D28: Scanlines, glass panels w/ backdrop blur, grid floor, film grain, 1px luminous borders
B29: Cinematic motion | C29: GSAP + Framer Motion | D29: Materialize/dematerialize transitions, camera timelines, UI springs; prefers-reduced-motion respected
B30: Voice I/O | C30: Web Speech API (keyless) | D30: STT command capture + TTS briefings work TODAY with zero API keys; upgrades to realtime voice models when LLM keys arrive (D3)
B31: Briefing engine | C31: event-driven narrator | D31: Situation summaries at milestones/gates/anomalies, spoken + rendered ('Round 2 complete, 3 candidates, budget 61%')
B32: Time-travel replay | C32: event-sourced state | D32: DVR scrubber through campaign epochs; forensic review of judge verdicts
B33: Copilot command core | C33: MCP tool servers | D33: Cmd-K natural-language command bar; conversation-first navigation; ask-the-swarm over findings/evidence
B36: Personas
B37: Persona | C37: Needs | D37: Primary Screens
B38: Red Operator | C38: Live campaign monitoring, payload triage, gate actions | D38: Mission Control, Findings, Technique Library
B39: Engagement Lead / CISO | C39: Scorecard, findings severity, remediation status | D39: Scorecard, Findings, Dossier
B40: Compliance officer | C40: Control mapping, evidence completeness, exports | D40: Dossier, Findings evidence drawer
B41: Exec sponsor | C41: Posture trend, business risk framing | D41: Command Center, Scorecard (HUD briefings)
B42: Admin | C42: RBAC/SSO, integrations, budgets, audit trail | D42: Admin & Governance
B45: Stack
B46: Layer | C46: Choices
B47: Frontend | C47: Next.js App Router + TypeScript + Tailwind + shadcn/ui (Radix)
B48: 3D / HUD | C48: react-three-fiber + drei + postprocessing (bloom); auto-fallback React Flow schematic
B49: Motion | C49: GSAP (cinematic timelines) + Framer Motion (UI springs)
B50: Data viz | C50: Recharts (scorecard/trends) + custom canvas telemetry
B51: Realtime | C51: FastAPI event bus: SSE typed events (agent_state_change, transcript_delta, verdict, budget_tick, gate_request, finding_created)
B52: State | C52: Event-sourced store with time-travel replay; virtualized transcript panes
B53: Voice | C53: Web Speech API now; realtime voice models when keys arrive
B54: Enterprise | C54: RBAC 5 roles, OIDC/SAML SSO, multi-tenant + white-label, view/export audit trail, WCAG 2.1 AA (Ops Mode), i18n-ready
B55: Design tokens | C55: Deep-space navy base, cyan glow primary, amber warn / red critical; Space Grotesk/Chakra Petch display + JetBrains Mono telemetry
B57: Effort: UI total ~+60-75% over pre-UI plan (Ops console +25-35%, HUD layer +30-40%). Phased so probability holds ~92-95%; cinematic-first would drop it to ~85%.
B58: Guardrails (D7): prefers-reduced-motion respected; HUD Mode = presentation/war-room layer; Ops Mode carries WCAG 2.1 AA; 3D lazy-loaded with 60fps budget; auto-degrade to schematic DAG.

Sheet Build Plan
B2: Build Plan — 12 Weeks to Lighthouse Beta (38 tasks; v1.1 T23 split)
B4: ID | C4: Workstream | D4: Task | E4: Owner | F4: Start Wk | G4: End Wk | H4: Depends On | I4: Deliverable | J4: Status | K4: % Done | L4: W1 | M4: W2 | N4: W3 | O4: W4 | P4: W5 | Q4: W6 | R4: W7 | S4: W8 | T4: W9 | U4: W10 | V4: W11 | W4: W12
B5: T01 | C5: WS1 Core | D5: Finding schema + transcript evidence contract | E5: Arch | F5: 1 | G5: 1 | H5: - | I5: Schema v1 | J5: Not Started | K5: 0 | L5: =IF(AND(COLUMN()-11>=$F5,COLUMN()-11<=$G5),"#","") -> # | M5: =IF(AND(COLUMN()-11>=$F5,COLUMN()-11<=$G5),"#","") | N5: =IF(AND(COLUMN()-11>=$F5,COLUMN()-11<=$G5),"#","") | O5: =IF(AND(COLUMN()-11>=$F5,COLUMN()-11<=$G5),"#","") | P5: =IF(AND(COLUMN()-11>=$F5,COLUMN()-11<=$G5),"#","") | Q5: =IF(AND(COLUMN()-11>=$F5,COLUMN()-11<=$G5),"#","") | R5: =IF(AND(COLUMN()-11>=$F5,COLUMN()-11<=$G5),"#","") | S5: =IF(AND(COLUMN()-11>=$F5,COLUMN()-11<=$G5),"#","") | ... W5: =IF(AND(COLUMN()-11>=$F5,COLUMN()-11<=$G5),"#","")
B6: T02 | C6: WS1 Core | D6: Technique catalog v1 (40 techniques, OWASP/ATLAS mapped) | E6: ASE1 | F6: 1 | G6: 2 | H6: T01 | I6: Technique catalog v1 | J6: Not Started | K6: 0 | L6: =IF(AND(COLUMN()-11>=$F6,COLUMN()-11<=$G6),"#","") -> # | M6: =IF(AND(COLUMN()-11>=$F6,COLUMN()-11<=$G6),"#","") -> # | N6: =IF(AND(COLUMN()-11>=$F6,COLUMN()-11<=$G6),"#","") | O6: =IF(AND(COLUMN()-11>=$F6,COLUMN()-11<=$G6),"#","") | P6: =IF(AND(COLUMN()-11>=$F6,COLUMN()-11<=$G6),"#","") | Q6: =IF(AND(COLUMN()-11>=$F6,COLUMN()-11<=$G6),"#","") | R6: =IF(AND(COLUMN()-11>=$F6,COLUMN()-11<=$G6),"#","") | S6: =IF(AND(COLUMN()-11>=$F6,COLUMN()-11<=$G6),"#","") | ... W6: =IF(AND(COLUMN()-11>=$F6,COLUMN()-11<=$G6),"#","")
B7: T03 | C7: WS1 Core | D7: Judge framework: rule detectors + LLM-as-judge + combine | E7: ASE2 | F7: 1 | G7: 2 | H7: T01 | I7: mcp-judge v0 | J7: Not Started | K7: 0 | L7: =IF(AND(COLUMN()-11>=$F7,COLUMN()-11<=$G7),"#","") -> # | M7: =IF(AND(COLUMN()-11>=$F7,COLUMN()-11<=$G7),"#","") -> # | N7: =IF(AND(COLUMN()-11>=$F7,COLUMN()-11<=$G7),"#","") | O7: =IF(AND(COLUMN()-11>=$F7,COLUMN()-11<=$G7),"#","") | P7: =IF(AND(COLUMN()-11>=$F7,COLUMN()-11<=$G7),"#","") | Q7: =IF(AND(COLUMN()-11>=$F7,COLUMN()-11<=$G7),"#","") | R7: =IF(AND(COLUMN()-11>=$F7,COLUMN()-11<=$G7),"#","") | S7: =IF(AND(COLUMN()-11>=$F7,COLUMN()-11<=$G7),"#","") | ... W7: =IF(AND(COLUMN()-11>=$F7,COLUMN()-11<=$G7),"#","")
B8: T04 | C8: WS1 Core | D8: OPA severity + scorecard dimension rules | E8: ASE1 | F8: 1 | G8: 2 | H8: T01 | I8: Rego pack v0 | J8: Not Started | K8: 0 | L8: =IF(AND(COLUMN()-11>=$F8,COLUMN()-11<=$G8),"#","") -> # | M8: =IF(AND(COLUMN()-11>=$F8,COLUMN()-11<=$G8),"#","") -> # | N8: =IF(AND(COLUMN()-11>=$F8,COLUMN()-11<=$G8),"#","") | O8: =IF(AND(COLUMN()-11>=$F8,COLUMN()-11<=$G8),"#","") | P8: =IF(AND(COLUMN()-11>=$F8,COLUMN()-11<=$G8),"#","") | Q8: =IF(AND(COLUMN()-11>=$F8,COLUMN()-11<=$G8),"#","") | R8: =IF(AND(COLUMN()-11>=$F8,COLUMN()-11<=$G8),"#","") | S8: =IF(AND(COLUMN()-11>=$F8,COLUMN()-11<=$G8),"#","") | ... W8: =IF(AND(COLUMN()-11>=$F8,COLUMN()-11<=$G8),"#","")
B9: T05 | C9: WS2 Targets | D9: Target adapter (OpenAI-compat + tool calls) | E9: ASE2 | F9: 2 | G9: 3 | H9: T01 | I9: mcp-target-adapter | J9: Not Started | K9: 0 | L9: =IF(AND(COLUMN()-11>=$F9,COLUMN()-11<=$G9),"#","") | M9: =IF(AND(COLUMN()-11>=$F9,COLUMN()-11<=$G9),"#","") -> # | N9: =IF(AND(COLUMN()-11>=$F9,COLUMN()-11<=$G9),"#","") -> # | O9: =IF(AND(COLUMN()-11>=$F9,COLUMN()-11<=$G9),"#","") | P9: =IF(AND(COLUMN()-11>=$F9,COLUMN()-11<=$G9),"#","") | Q9: =IF(AND(COLUMN()-11>=$F9,COLUMN()-11<=$G9),"#","") | R9: =IF(AND(COLUMN()-11>=$F9,COLUMN()-11<=$G9),"#","") | S9: =IF(AND(COLUMN()-11>=$F9,COLUMN()-11<=$G9),"#","") | ... W9: =IF(AND(COLUMN()-11>=$F9,COLUMN()-11<=$G9),"#","")
B10: T06 | C10: WS2 Targets | D10: Browser automation adapter for chat UIs | E10: ASE2 | F10: 3 | G10: 4 | H10: T05 | I10: mcp-browser | J10: Not Started | K10: 0 | L10: =IF(AND(COLUMN()-11>=$F10,COLUMN()-11<=$G10),"#","") | M10: =IF(AND(COLUMN()-11>=$F10,COLUMN()-11<=$G10),"#","") | N10: =IF(AND(COLUMN()-11>=$F10,COLUMN()-11<=$G10),"#","") -> # | O10: =IF(AND(COLUMN()-11>=$F10,COLUMN()-11<=$G10),"#","") -> # | P10: =IF(AND(COLUMN()-11>=$F10,COLUMN()-11<=$G10),"#","") | Q10: =IF(AND(COLUMN()-11>=$F10,COLUMN()-11<=$G10),"#","") | R10: =IF(AND(COLUMN()-11>=$F10,COLUMN()-11<=$G10),"#","") | S10: =IF(AND(COLUMN()-11>=$F10,COLUMN()-11<=$G10),"#","") | ... W10: =IF(AND(COLUMN()-11>=$F10,COLUMN()-11<=$G10),"#","")
B11: T07 | C11: WS2 Targets | D11: Canary/honeytoken framework + webhook listener | E11: ASE1 | F11: 2 | G11: 3 | H11: T01 | I11: mcp-canary | J11: Not Started | K11: 0 | L11: =IF(AND(COLUMN()-11>=$F11,COLUMN()-11<=$G11),"#","") | M11: =IF(AND(COLUMN()-11>=$F11,COLUMN()-11<=$G11),"#","") -> # | N11: =IF(AND(COLUMN()-11>=$F11,COLUMN()-11<=$G11),"#","") -> # | O11: =IF(AND(COLUMN()-11>=$F11,COLUMN()-11<=$G11),"#","") | P11: =IF(AND(COLUMN()-11>=$F11,COLUMN()-11<=$G11),"#","") | Q11: =IF(AND(COLUMN()-11>=$F11,COLUMN()-11<=$G11),"#","") | R11: =IF(AND(COLUMN()-11>=$F11,COLUMN()-11<=$G11),"#","") | S11: =IF(AND(COLUMN()-11>=$F11,COLUMN()-11<=$G11),"#","") | ... W11: =IF(AND(COLUMN()-11>=$F11,COLUMN()-11<=$G11),"#","")
B12: T08 | C12: WS3 Packs | D12: PIN pack v1 (10 techniques, seeds + variants) | E12: PE | F12: 3 | G12: 4 | H12: T02 | I12: PIN pack + evals | J12: Not Started | K12: 0 | L12: =IF(AND(COLUMN()-11>=$F12,COLUMN()-11<=$G12),"#","") | M12: =IF(AND(COLUMN()-11>=$F12,COLUMN()-11<=$G12),"#","") | N12: =IF(AND(COLUMN()-11>=$F12,COLUMN()-11<=$G12),"#","") -> # | O12: =IF(AND(COLUMN()-11>=$F12,COLUMN()-11<=$G12),"#","") -> # | P12: =IF(AND(COLUMN()-11>=$F12,COLUMN()-11<=$G12),"#","") | Q12: =IF(AND(COLUMN()-11>=$F12,COLUMN()-11<=$G12),"#","") | R12: =IF(AND(COLUMN()-11>=$F12,COLUMN()-11<=$G12),"#","") | S12: =IF(AND(COLUMN()-11>=$F12,COLUMN()-11<=$G12),"#","") | ... W12: =IF(AND(COLUMN()-11>=$F12,COLUMN()-11<=$G12),"#","")
B13: T09 | C13: WS3 Packs | D13: EXF pack v1 (7 techniques, canary-driven) | E13: PE | F13: 3 | G13: 4 | H13: T07 | I13: EXF pack + evals | J13: Not Started | K13: 0 | L13: =IF(AND(COLUMN()-11>=$F13,COLUMN()-11<=$G13),"#","") | M13: =IF(AND(COLUMN()-11>=$F13,COLUMN()-11<=$G13),"#","") | N13: =IF(AND(COLUMN()-11>=$F13,COLUMN()-11<=$G13),"#","") -> # | O13: =IF(AND(COLUMN()-11>=$F13,COLUMN()-11<=$G13),"#","") -> # | P13: =IF(AND(COLUMN()-11>=$F13,COLUMN()-11<=$G13),"#","") | Q13: =IF(AND(COLUMN()-11>=$F13,COLUMN()-11<=$G13),"#","") | R13: =IF(AND(COLUMN()-11>=$F13,COLUMN()-11<=$G13),"#","") | S13: =IF(AND(COLUMN()-11>=$F13,COLUMN()-11<=$G13),"#","") | ... W13: =IF(AND(COLUMN()-11>=$F13,COLUMN()-11<=$G13),"#","")
B14: T10 | C14: WS3 Packs | D14: AGE/OUT packs v1 (11 techniques) | E14: ASE1 | F14: 4 | G14: 5 | H14: T05 | I14: AGE+OUT packs | J14: Not Started | K14: 0 | L14: =IF(AND(COLUMN()-11>=$F14,COLUMN()-11<=$G14),"#","") | M14: =IF(AND(COLUMN()-11>=$F14,COLUMN()-11<=$G14),"#","") | N14: =IF(AND(COLUMN()-11>=$F14,COLUMN()-11<=$G14),"#","") | O14: =IF(AND(COLUMN()-11>=$F14,COLUMN()-11<=$G14),"#","") -> # | P14: =IF(AND(COLUMN()-11>=$F14,COLUMN()-11<=$G14),"#","") -> # | Q14: =IF(AND(COLUMN()-11>=$F14,COLUMN()-11<=$G14),"#","") | R14: =IF(AND(COLUMN()-11>=$F14,COLUMN()-11<=$G14),"#","") | S14: =IF(AND(COLUMN()-11>=$F14,COLUMN()-11<=$G14),"#","") | ... W14: =IF(AND(COLUMN()-11>=$F14,COLUMN()-11<=$G14),"#","")
B15: T11 | C15: WS3 Packs | D15: MEM/CON/HAL/SUP packs v1 (12 techniques) | E15: ASE2 | F15: 4 | G15: 5 | H15: T02 | I15: Remaining packs | J15: Not Started | K15: 0 | L15: =IF(AND(COLUMN()-11>=$F15,COLUMN()-11<=$G15),"#","") | M15: =IF(AND(COLUMN()-11>=$F15,COLUMN()-11<=$G15),"#","") | N15: =IF(AND(COLUMN()-11>=$F15,COLUMN()-11<=$G15),"#","") | O15: =IF(AND(COLUMN()-11>=$F15,COLUMN()-11<=$G15),"#","") -> # | P15: =IF(AND(COLUMN()-11>=$F15,COLUMN()-11<=$G15),"#","") -> # | Q15: =IF(AND(COLUMN()-11>=$F15,COLUMN()-11<=$G15),"#","") | R15: =IF(AND(COLUMN()-11>=$F15,COLUMN()-11<=$G15),"#","") | S15: =IF(AND(COLUMN()-11>=$F15,COLUMN()-11<=$G15),"#","") | ... W15: =IF(AND(COLUMN()-11>=$F15,COLUMN()-11<=$G15),"#","")
B16: T12 | C16: WS4 MCP | D16: PyRIT + Garak + promptfoo MCP wrappers | E16: ASE2 | F16: 5 | G16: 6 | H16: T05 | I16: 3 attack servers | J16: Not Started | K16: 0 | L16: =IF(AND(COLUMN()-11>=$F16,COLUMN()-11<=$G16),"#","") | M16: =IF(AND(COLUMN()-11>=$F16,COLUMN()-11<=$G16),"#","") | N16: =IF(AND(COLUMN()-11>=$F16,COLUMN()-11<=$G16),"#","") | O16: =IF(AND(COLUMN()-11>=$F16,COLUMN()-11<=$G16),"#","") | P16: =IF(AND(COLUMN()-11>=$F16,COLUMN()-11<=$G16),"#","") -> # | Q16: =IF(AND(COLUMN()-11>=$F16,COLUMN()-11<=$G16),"#","") -> # | R16: =IF(AND(COLUMN()-11>=$F16,COLUMN()-11<=$G16),"#","") | S16: =IF(AND(COLUMN()-11>=$F16,COLUMN()-11<=$G16),"#","") | ... W16: =IF(AND(COLUMN()-11>=$F16,COLUMN()-11<=$G16),"#","")
... B42: T36 | C42: WS9 GTM | D42: Certify 3 delivery pods + training | E42: Arch | F42: 12 | G42: 12 | H42: T29 | I42: 3 certified pods | J42: Not Started | K42: 0 | L42: =IF(AND(COLUMN()-11>=$F42,COLUMN()-11<=$G42),"#","") | M42: =IF(AND(COLUMN()-11>=$F42,COLUMN()-11<=$G42),"#","") | N42: =IF(AND(COLUMN()-11>=$F42,COLUMN()-11<=$G42),"#","") | O42: =IF(AND(COLUMN()-11>=$F42,COLUMN()-11<=$G42),"#","") | P42: =IF(AND(COLUMN()-11>=$F42,COLUMN()-11<=$G42),"#","") | Q42: =IF(AND(COLUMN()-11>=$F42,COLUMN()-11<=$G42),"#","") | R42: =IF(AND(COLUMN()-11>=$F42,COLUMN()-11<=$G42),"#","") | S42: =IF(AND(COLUMN()-11>=$F42,COLUMN()-11<=$G42),"#","") | ... W42: =IF(AND(COLUMN()-11>=$F42,COLUMN()-11<=$G42),"#","") -> #
B44: Owners: Arch=AI Security Architect, ASE1/ASE2=AI Security Engineers, PE=Prompt Engineer, AE=Agentic Engineer, RT=Red Teamer, EL=Engagement Lead.
B45: Go/no-go: internal PoC (T25-T27) must find real vulns with FP <=10% before any client run; ROAI legal template (T29) blocks beta without signature.
B46: v1.1: T23 split into T23a/b/c (Console foundation > live > HUD layer). Exec Milestones sheet carries demo execution sequencing; CI-gate rides Sentinel view.

Sheet Exec Milestones
B2: Execution Milestones — Demo Plan M0-M6c (v1.1)
B4: Demo execution sequencing — supersedes Build Plan ordering for the Tier-1 demo (D1)
B5: M# | C5: Scope | D5: Blueprint Tasks | E5: Acceptance Gate | F5: Status | G5: % Done
B6: M0 | C6: Foundation: finding/transcript schema, technique catalog v1 as data, skeleton | D6: T01-T02 | E6: 40 techniques load, IDs unique | F6: Done | G6: 100
B7: M1 | C7: Target plane: mcp-target-adapter + mock vulnerable demo target (seeded flaws per pack) + canary framework w/ local webhook detector | D7: T05, T07 | E7: >=1 flaw per pack; canary hit detected | F7: Done | G7: 100
B8: M2 | C8: Judging & scoring: dual-mode judge (rules + LLM stub) + scoring engine (real Rego via OPA binary; Python fallback) | D8: T03-T04 | E8: Scorecard reproduces workbook math exactly | F8: Done | G8: 100
B9: M3 | C9: MCP live: 6 P0 servers built & registered in ZCode (target-adapter, pyrit-thin, judge, canary, opa/scorer, evidence) | D9: MCP sheet P0 | E9: mcp__redforge__* tools callable in-session | F9: Done | G9: 100
B10: M4 | C10: Swarm: 14-node DAG runner, bounded 3-round mutation, budget caps, Gatekeeper interrupts | D10: T13-T19 | E10: Epoch runs acyclic; caps enforced; gates fire | F10: Done | G10: 100
B11: M5 | C11: Evidence & reporting: evidence store, findings register, Verifier FP-kill, Scribe citation lint, compliance mapping, report export | D11: T20-T22 | E11: Every report claim cites finding_id | F11: Done | G11: 100
B12: M6a | C12: Console foundation: app shell, design tokens, routing, all 10 screens with fixture data (Ops Mode) | D12: T23a | E12: All 10 screens render with fixture data | F12: Done | G12: 100
B13: M6b | C13: Mission Control live: SSE event bus, live DAG, streaming transcripts, gate inbox + Findings/Scorecard/Dossier views | D13: T23b | E13: Live campaign drives the UI end-to-end | F13: Done | G13: 100
B14: M6b+ | C14: HUD/JARVIS layer: 3D constellation, voice I/O (Web Speech), Copilot command core, briefing engine, materialization motion, replay scrubber | D14: T23c | E14: Cinematic demo runs in HUD Mode; Ops Mode still AA; 60fps budget held | F14: Done | G14: 100
B15: M6c | C15: E2E demo: full A0-A5 campaign vs demo target through Console + MCP; FP <=10% on fixture | D15: T25-T28 | E15: Campaign completes; scorecard + dossier generated | F15: Done | G15: 100
B16: M7 | C16: World View (D8): full-screen 3D world — GLSL core orb + sunburst dial, living 9-node constellation w/ G1/G2 diamond gates (event physics via world-bus), diegetic instruments (reactor/radar/audio/diagnostics/terminal/objective banner), voice captions + command echo, camera fly-to + node/gate holograms w/ signature bridge, replay timeline, violet/navy themes, offline demo loop; SSE delivery bugs Q-11/Q-12 fixed w/ regression test | D16: D8 build | E16: E2E world leg: campaign driven from /world; holograms + theme verified; ≥95% suite pass | F16: Done | G16: 100
B17: M8 | C17: Boot ritual + living sky (D9): OrchestratorHead (12k GPU particles, featureless silhouette, speech pulse, neck streamers), ReadinessPrompt (voice + YES), staggered constellation bloom + instrument reveal, SkyTraffic (rockets 2min / meteoroids 1min, pooled), handoff blink-lines + packet streams (once per handoff); boot routing (?boot=skip, sessionStorage fast-path, join-running); E2E boot leg | D17: D9 build | E17: E2E: head assembles, YES clicked, 11 planets bloom, instruments live; ≥95% suite pass | F17: Done | G17: 100
B19: Gates are hard: a milestone is Done only when its gate passes. HUD (M6b+) never blocks functional milestones — the cinematic layer is additive (D7).
B20: M0-M5 run engine-first; M6a-M6c build the Console; M3 makes the campaign drivable from ZCode via MCP tools.

Sheet KPI Tracker
B2: KPI Tracker — Direction-Aware (enter Actuals in blue)
B4: Family | C4: KPI | D4: Definition / Formula | E4: Direction | F4: Target | G4: Actual | H4: Status | I4: Owner | J4: Frequency
B5: Delivery | C5: Time-to-first-finding | D5: hours from A1 exit to first confirmed finding | E5: Lower | F5: 72 | H5: =IF(G5="","-",IF($E5="Higher",IF(G5>=$F5,"On Target",IF(G5>=0.8*$F5,"At Risk","Off Target")),IF(G5<=$F5,"On Target",IF(G5<=1.2*$F5,"At Risk","Off Target")))) | I5: EL | J5: per engagement
B6: Delivery | C6: Technique-pack coverage | D6: packs executed / packs planned (%) | E6: Higher | F6: 90 | H6: =IF(G6="","-",IF($E6="Higher",IF(G6>=$F6,"On Target",IF(G6>=0.8*$F6,"At Risk","Off Target")),IF(G6<=$F6,"On Target",IF(G6<=1.2*$F6,"At Risk","Off Target")))) | I6: EL | J6: per engagement
B7: Delivery | C7: Quick-win report SLA | D7: hours from kickoff to quick-win report | E7: Lower | F7: 72 | H7: =IF(G7="","-",IF($E7="Higher",IF(G7>=$F7,"On Target",IF(G7>=0.8*$F7,"At Risk","Off Target")),IF(G7<=$F7,"On Target",IF(G7<=1.2*$F7,"At Risk","Off Target")))) | I7: EL | J7: per engagement
B8: Delivery | C8: Judge-verifier agreement | D8: verdicts confirmed unchanged / total (%) | E8: Higher | F8: 80 | H8: =IF(G8="","-",IF($E8="Higher",IF(G8>=$F8,"On Target",IF(G8>=0.8*$F8,"At Risk","Off Target")),IF(G8<=$F8,"On Target",IF(G8<=1.2*$F8,"At Risk","Off Target")))) | I8: ASE1 | J8: per engagement
B9: Client outcome | C9: Injection success reduction @90d | D9: critical PIN success post-fix vs baseline (%) | E9: Lower | F9: 5 | H9: =IF(G9="","-",IF($E9="Higher",IF(G9>=$F9,"On Target",IF(G9>=0.8*$F9,"At Risk","Off Target")),IF(G9<=$F9,"On Target",IF(G9<=1.2*$F9,"At Risk","Off Target")))) | I9: EL | J9: 90-day post-fix
B10: Client outcome | C10: Guardrail regression catch | D10: updates caught by Sentinel retest (%) | E10: Higher | F10: 100 | H10: =IF(G10="","-",IF($E10="Higher",IF(G10>=$F10,"On Target",IF(G10>=0.8*$F10,"At Risk","Off Target")),IF(G10<=$F10,"On Target",IF(G10<=1.2*$F10,"At Risk","Off Target")))) | I10: AE | J10: continuous
B11: Client outcome | C11: Mean time-to-patch guardrail | D11: finding > patched guardrail (hours) | E11: Lower | F11: 168 | H11: =IF(G11="","-",IF($E11="Higher",IF(G11>=$F11,"On Target",IF(G11>=0.8*$F11,"At Risk","Off Target")),IF(G11<=$F11,"On Target",IF(G11<=1.2*$F11,"At Risk","Off Target")))) | I11: EL | J11: per finding
B12: Client outcome | C12: Regulatory evidence readiness | D12: findings with control mapping + evidence (%) | E12: Higher | F12: 100 | H12: =IF(G12="","-",IF($E12="Higher",IF(G12>=$F12,"On Target",IF(G12>=0.8*$F12,"At Risk","Off Target")),IF(G12<=$F12,"On Target",IF(G12<=1.2*$F12,"At Risk","Off Target")))) | I12: EL | J12: per engagement
B13: Swarm ops | C13: Autonomy rate | D13: steps without human / total (%) | E13: Higher | F13: 90 | H13: =IF(G13="","-",IF($E13="Higher",IF(G13>=$F13,"On Target",IF(G13>=0.8*$F13,"At Risk","Off Target")),IF(G13<=$F13,"On Target",IF(G13<=1.2*$F13,"At Risk","Off Target")))) | I13: AE | J13: per engagement
B14: Swarm ops | C14: Interventions per engagement | D14: human interventions (all at gates) | E14: Lower | F14: 5 | H14: =IF(G14="","-",IF($E14="Higher",IF(G14>=$F14,"On Target",IF(G14>=0.8*$F14,"At Risk","Off Target")),IF(G14<=$F14,"On Target",IF(G14<=1.2*$F14,"At Risk","Off Target")))) | I14: AE | J14: per engagement
B15: Swarm ops | C15: False-positive rate | D15: verifier-voided / reported findings (%) | E15: Lower | F15: 10 | H15: =IF(G15="","-",IF($E15="Higher",IF(G15>=$F15,"On Target",IF(G15>=0.8*$F15,"At Risk","Off Target")),IF(G15<=$F15,"On Target",IF(G15<=1.2*$F15,"At Risk","Off Target")))) | I15: ASE1 | J15: per engagement
B16: Swarm ops | C16: Delivery cost ratio | D16: delivery cost / deal value (%) | E16: Lower | F16: 35 | H16: =IF(G16="","-",IF($E16="Higher",IF(G16>=$F16,"On Target",IF(G16>=0.8*$F16,"At Risk","Off Target")),IF(G16<=$F16,"On Target",IF(G16<=1.2*$F16,"At Risk","Off Target")))) | I16: EL | J16: per deal
... B18: Business | C18: Assess > Continuous conversion | D18: continuous / assessments (%) | E18: Higher | F18: 50 | H18: =IF(G18="","-",IF($E18="Higher",IF(G18>=$F18,"On Target",IF(G18>=0.8*$F18,"At Risk","Off Target")),IF(G18<=$F18,"On Target",IF(G18<=1.2*$F18,"At Risk","Off Target")))) | I18: EL | J18: quarterly
B20: Direction-aware: Higher-is-better floors at 80% of target for At Risk; Lower-is-better ceilings at 120%. Blank actual shows '-'.

Sheet Risk Register
B2: Risk Register — Live L x I Scoring (edit blue cells)
B4: ID | C4: Risk | D4: Category | E4: Likelihood (1-5) | F4: Impact (1-5) | G4: Score | H4: Mitigation | I4: Owner | J4: Status
B5: R01 | C5: Testing the bare model instead of the deployed system | D5: Method | E5: 3 | F5: 4 | G5: =E5*F5 -> 12 | H5: Tenet enforced: target adapter requires deployed-app endpoint; surface map proves it | I5: Arch | J5: Open
B6: R02 | C6: Production attack causes outage or customer harm | D6: Safety | E6: 2 | F6: 5 | G6: =E6*F6 -> 10 | H6: ROAI + rate caps + budget meters + sandbox-first; sensitive packs behind G1 | I6: RT | J6: Open
B7: R03 | C7: Judge false positives erode client trust | D7: Quality | E7: 3 | F7: 4 | G7: =E7*F7 -> 12 | H7: Dual-mode judging; verifier FP-kill; agreement KPI >=80%; human-confirmed criticals | I7: ASE1 | J7: Open
B8: R04 | C8: Real PII leaves target boundary during EXF tests | D8: Compliance | E8: 2 | F8: 5 | G8: =E8*F8 -> 10 | H8: Canary/honeytoken-only exfiltration proofs; payload safety screen; DPA in ROAI | I8: EL | J8: Open
B9: R05 | C9: Model/guardrail updates invalidate baselines | D9: Technical | E9: 4 | F9: 3 | G9: =E9*F9 -> 12 | H9: Sentinel 24h update detection; automated regression suite; versioned baselines | I9: AE | J9: Open
B10: R06 | C10: Target sprawl (every team ships a new copilot) | D10: Scope | E10: 4 | F10: 3 | G10: =E10*F10 -> 12 | H10: ROAI enumerates targets; class-based scoping; per-target pricing | I10: EL | J10: Open
B11: R07 | C11: Prompt-injection specialist scarcity | D11: People | E11: 3 | F11: 3 | G11: =E11*F11 -> 9 | H11: Train SCA/DAST engineers via pack runbooks; prompt-engineer upskilling; academy | I11: Arch | J11: Open
B12: R08 | C12: Technique library ages vs fast-moving attacks | D12: Market | E12: 3 | F12: 4 | G12: =E12*F12 -> 12 | H12: Monthly threat-intel pack pipeline; community probes (Garak/PyRIT updates); ATLAS tracking | I12: ASE2 | J12: Open
B13: R09 | C13: Client treats report as one-off, no continuous | D13: Business | E13: 3 | F13: 3 | G13: =E13*F13 -> 9 | H13: Regulatory evidence needs recurring (AI Act Art 15); Sentinel value story; conversion KPI | I13: EL | J13: Open
B14: R10 | C14: Lighthouse copilot project slips | D14: Market | E14: 3 | F14: 4 | G14: =E14*F14 -> 12 | H14: Two lighthouse candidates; internal copilot as fallback showcase | I14: EL | J14: Open
B16: RAG: score >=15 red / 8-14 amber / <8 green. R02 and R04 are hard safety gates — any breach halts the campaign.

Sheet Context Memory
B2: Context Memory — Decisions, Environment, Quirks, Sessions (v1.1)
B4: Locked decisions (full log: AI_RedForge_Project_Memory.md)
B5: # | C5: Decision | D5: Status
B6: D1 | C6: Target = Tier-1 technical demo (M0-M6c): full swarm, 6 P0 MCP servers, 40-technique corpus, dual-mode judge, scorecard, report vs vulnerable demo target | D6: Locked S1
B7: D2 | C7: Tier-3 GTM items (T29-T36: beta SOW, pricing, certified pods) OUT of scope — human/org work, not code | D7: Locked S1
B8: D3 | C8: LLM API keys deferred (user adds later). Demo-mode-first: offline scripted providers; real mode = .env flip | D8: Locked S3
B9: D4 | C9: Docker optional, not a blocker. SQLite (sqlalchemy+aiosqlite) for Postgres; filesystem for S3; OPA binary available so real Rego usable | D9: Locked S2
B10: D5 | C10: Agentic UI first-class: RedForge Console, enterprise grade (was only thin portal line L5/T23) | D10: Locked S3
B11: D6 | C11: Reference architecture: threat-modelling-agent-master (FastAPI + Next.js swarm, mission-control streaming, trace replay, SQLite) | D11: Locked S1
B12: D7 | C12: JARVIS-level UI as dual-mode: Ops Mode (audit default) + HUD Mode (cinematic) on ONE event stream; voice keyless via Web Speech API; phased so gates never depend on shader polish | D12: Locked S4
B13: D8 | C13: World View (from user's 2 reference reels, decoded frame-by-frame): the screen IS a 3D world at /world — protagonist core orb (GLSL fresnel+fbm, sunburst tick dial, orbits, dust), 9-node swarm constellation + G1/G2 diamond gates with event-driven pulses/impacts, diegetic DOM instruments (reactor gauges, fleet radar, audio field, MCP diagnostics, typewriter terminal, glass PRIMARY OBJECTIVE banner), voice captions + command echo, camera fly-to + node holograms with gate signature bridge, replay timeline; violet/navy themes; offline scripted demo loop; ops mode untouched (route groups) | D13: Locked S7
B14: D9 | C14: Entry Sequence / boot ritual (from user's 3rd reel Video-11678, decoded frame-by-frame): the world BOOTS as a ritual — ~12k molecule particles assemble a FEATURELESS humanoid head silhouette (D9 amendment: no eyes/brows/mouth/nose, overall shape only) via GPU vertex-shader convergence (bezier + per-particle stagger); the Orchestrator then asks 'are you ready?' answered by VOICE (Web Speech) or a glass YES button; on YES the agent planets bloom around him in stagger (~400ms each, elastic) with links drawing in; instruments materialize sequentially after; the sky lives on: rockets cross edge-to-edge every ~2min, fiery-tail meteoroids every ~1min; agent handoffs blink the connecting line 3x with a 6-packet stream, fired ONCE per transition. Guards: ?boot=skip for E2E, sessionStorage fast-path on repeat visits, join-live when a campaign is running, reduced-motion fallback | D14: Locked S8
B17: Environment readiness (installed & smoke-tested Sep 10 2026)
B18: Block | C18: Weight | D18: Status | E18: Achieved | F18: Detail
B19: Core API stack (fastapi/uvicorn/pydantic/httpx/jinja2) | C19: 10 | D19: PASS | E19: 10 | F19: fastapi 0.141.1, uvicorn 0.52.4, pydantic 2.13.5
B20: MCP SDK (mcp + fastmcp) | C20: 15 | D20: PASS | E20: 15 | F20: mcp 2.2.0 (MCPServer API) + fastmcp 4.0.3 (FastMCP API) — both verified
B21: Orchestration (langgraph) | C21: 10 | D21: PASS | E21: 10 | F21: langgraph 1.2.11
B22: Attack engine PyRIT | C22: 10 | D22: PASS | E22: 10 | F22: pyrit 1.1.0 (1.x layout: executor/score/memory)
B23: Attack engine Garak | C23: 5 | D23: PASS | E23: 5 | F23: garak 0.17.0
B24: Attack suite promptfoo | C24: 5 | D24: PASS | E24: 5 | F24: 0.123.0 via node entrypoint
B25: Scanner Giskard | C25: 5 | D25: PASS | E25: 5 | F25: giskard 3.0.0
B26: Browser automation (Playwright + Chromium) | C26: 10 | D26: PASS | E26: 10 | F26: playwright 1.62.0 + Chromium 151 headless
B27: Policy engine (OPA) | C27: 5 | D27: PASS | E27: 5 | F27: OPA 1.20.2 at .tools/opa.exe
B28: Evidence/data layer (sqlalchemy + aiosqlite + sqlite3) | C28: 10 | D28: PASS | E28: 10 | F28: sqlalchemy 2.0.52, sqlite 3.49.1
B29: LLM API access (real-attack mode) | C29: 0 | D29: DEFERRED | E29: 0 | F29: User adds keys later (D3); demo-mode covers M0-M6c
B30: Docker engine | C30: 5 | D30: PARTIAL | E30: 2.5 | F30: CLI 29.7.2 installed; engine needs admin wsl --install + reboot; optional per D4
B31: Total — readiness 87.5 / 90 = 97.2% (demo-critical 100%) | C31: 90 | E31: 87.5
B34: API quirks discovered (do not re-learn)
B35: # | C35: Topic | D35: Detail
B36: Q1 | C36: PyRIT 1.x new module layout | D36: pyrit.executor (attack/benchmark/promptgen/workflow), pyrit.score.llm_scoring, pyrit.memory.sqlite_memory; 0.x pyrit.orchestrator is GONE — mcp-pyrit targets 1.x
B37: Q2 | C37: MCP SDK 2.x rename | D37: Official FastMCP renamed MCPServer (mcp.server.mcpserver); standalone fastmcp keeps FastMCP — both installed & verified
B38: Q3 | C38: Git Bash path mangling | D38: .cmd shims + downloaded exes fail when invoked directly; promptfoo via node entrypoint.js, OPA via subprocess arg-list / cmd //c
B39: Q4 | C39: fastapi/starlette conflict | D39: fastapi upgraded 0.111 to 0.141.1 after MCP SDK pulled starlette 1.6.0 (resolved)
B40: Q5 | C40: httpx ASGITransport hangs on SSE | D40: Test the stream against a real uvicorn server (port 8971 fixture), never in-process ASGI transport
B41: Q6 | C41: Port 3000 occupied | D41: Belongs to threat-modeller reference app — console runs on 3100, API on 8000, api tests on 8971
B42: Q7 | C42: Port kill on Windows | D42: taskkill /F /T /PID by netstat lookup; TaskStop of npm leaves node children orphaned (EADDRINUSE next start)
B43: Q11 | C43: Next 15 rewrites buffer SSE bodies for browsers | D43: curl sees data, EventSource sees headers only → console EventSource targets API origin directly (NEXT_PUBLIC_API_BASE, default http://127.0.0.1:8000); API CORS allowlists :3000/:3100; SSE replays history on connect (late joiners OK)
B44: Q12 | C44: LiveCampaign.start() wiped SSE subscribers AND reset seq (FIXED S7) | D44: self.__init__() dropped every already-connected subscriber AND restarted seq at 1 while the stream gates on e.seq > sent — replayed-history clients silently discarded all new events; fixed by preserving subscribers + monotonic seq; airtight regression test test_sse_subscriber_survives_campaign_restart; old e2e text=JUDGE assertion had matched the DAG label and masked this
B47: Deferred items
B48: Item | C48: Next Step
B49: LLM API key | C49: User provides later; flip LLM_PROVIDER demo to real; activates real attacks + LLM-judge (+~5% outcome probability)
B50: Docker engine (optional) | C50: Admin: wsl --install, reboot, start Docker Desktop; only needed for containerized Postgres/S3/sandbox later
B51: Realtime voice models | C51: After keys arrive; Web Speech API covers HUD voice until then
B54: Session log
B55: Session | C55: Summary
B56: S1 2026-09-10 | C56: Full blueprint analysis; tiered outcome definition; milestone plan; P(Tier-1 demo)=85-90%, P(full blueprint incl. GTM)=10-15%
B57: S2 2026-09-10 | C57: Environment install campaign +77.5pts (10 to 87.5/100); quirks Q1-Q4 found; P(Tier-1) rose to 92-95%
B58: S3 2026-09-10 | C58: LLM-key block eliminated (97.2% env readiness; 100% demo-critical); Console UI plan added (D5); memory file created
B59: S4 2026-09-10 | C59: JARVIS-level UI locked as dual-mode (D7); M6b+ added; workbook regenerated v1.1 with Console UI / Exec Milestones / Context Memory sheets
B60: S5 2026-09-10 | C60: FULL BUILD via 8 parallel agents: repo redforge/ — M0-M5 gates ALL PASS, 143/143 pytest, 11/11 gates, E2E campaign 75 attempts/36 findings/8 packs confirmed, overall pass rate 100.0% (target 95%). 6 MCP servers registered in workspace .zcode/config.json (live on session restart). Console M6a DONE (10/10 routes, dark ops theme, production build). Run: scripts/run_gates.py, scripts/run_e2e.py; console: cd console && npm run dev
B61: S6 2026-09-10 | C61: REMAINING WORK COMPLETE (M6b/M6b+/M6c): Live API (SSE event bus, python -m redforge.api) + console live wiring (mission control live DAG/transcript/controls, gates countersign, findings, scorecard) + HUD/JARVIS layer (R3F 3D constellation w/ bloom, keyless Web-Speech voice briefings, Cmd-K copilot, time-travel replay, reduced-motion guardrail). Console-driven E2E PASS: 75 attempts, 36/36 confirmed, 8/8 packs, FP 0.0, score 48.9 Poor, PDF dossier. FINAL: 14/14 gates + 146/146 pytest = 100.0% pass rate. Console at localhost:3100 (3000 belongs to threat-modeller), API at :8000.
B62: S7 2026-09-11 | C62: WORLD VIEW BUILT (D8, M7) from user's 2 reference reels (decoded frame-by-frame): /world full-screen 3D scene — GLSL core orb + sunburst dial + orbits + dust + grid + starfield + post-FX (bloom/chromatic/scanline/grain/vignette); 9-node constellation + G1/G2 diamond gates with event-driven pulses/impacts (world-bus); diegetic instruments (reactor, fleet radar, audio field, MCP diagnostics, typewriter terminal, glass objective banner); voice captions + command echo; camera fly-to + node/gate holograms w/ signature bridge; replay timeline; violet/navy themes; offline demo loop. Two real SSE bugs found+fixed: Q-11 (Next rewrite buffers SSE body for browsers → direct-origin EventSource + CORS :3100), Q-12 (start() wiped subscriber queues → fixed + regression test; old e2e assertion had masked it). pytest 147/147. Console v0.7.0-m7-world.
B63: S8 2026-09-11 | C63: PLANETS + 4K CLARITY + BOOT RITUAL (D8 polish, D9): every agent became a distinct procedural planet (banded gas giant OPERATORS w/ ring, Uranus-tilted SENTINEL, star SCORER, ringed SCOUT, moons) via one shared GLSL planet shader (bands/fbm/terminator/fresnel atmosphere); clarity pass (full DPR≤2.75, MSAA×4, grain/scanline/CA near-subliminal, text smoothing); D9 boot ritual built from 3rd reel: featureless particle head (user amendment) → readiness prompt (voice+YES) → staggered planet bloom + instrument reveal → living sky (rockets/meteoroids) → handoff packet choreography. Fixed Float32Array.set 4-wide-row overflow (head geometry). Console v0.8.0-m8-ritual.
B65: This sheet + the memory file are the single source of continuity across sessions; update both together.

Sheet Review
B2: Review — Live Cross-Validation (all rows must show PASS)
B4: Check | C4: Expected | D4: Actual | E4: Status
B5: Scoring weights total 100% | C5: 1 | D5: ='Scoring Model'!C12 -> 1 | E5: =IF(ROUND(C5,4)=ROUND(D5,4),"PASS","FAIL") -> PASS
B6: Technique catalog count | C6: 40 | D6: =COUNTA('Technique Catalog'!B5:B44) -> 40 | E6: =IF(ROUND(C6,2)=ROUND(D6,2),"PASS","FAIL") -> PASS
B7: Technique IDs unique (0 duplicates) | C7: 0 | D7: =SUMPRODUCT((COUNTIF('Technique Catalog'!B5:B44,'Technique Catalog'!B5:B44)>1)*1) -> 0 | E7: =IF(ROUND(C7,2)=ROUND(D7,2),"PASS","FAIL") -> PASS
B8: Build plan task count | C8: 38 | D8: =COUNTA('Build Plan'!B5:B42) -> 38 | E8: =IF(ROUND(C8,2)=ROUND(D8,2),"PASS","FAIL") -> PASS
B9: Gantt integrity (start<=end for all) | C9: 38 | D9: =SUMPRODUCT(('Build Plan'!F5:F42<='Build Plan'!G5:G42)*1) -> 38 | E9: =IF(ROUND(C9,2)=ROUND(D9,2),"PASS","FAIL") -> PASS
B10: KPI count | C10: 14 | D10: =COUNTA('KPI Tracker'!C5:C18) -> 14 | E10: =IF(ROUND(C10,2)=ROUND(D10,2),"PASS","FAIL") -> PASS
B11: Risk count | C11: 10 | D11: =COUNTA('Risk Register'!B5:B14) -> 10 | E11: =IF(ROUND(C11,2)=ROUND(D11,2),"PASS","FAIL") -> PASS
B12: Risk scores within 1-25 | C12: 10 | D12: =SUMPRODUCT(('Risk Register'!G5:G14>=1)*('Risk Register'!G5:G14<=25)) -> 10 | E12: =IF(ROUND(C12,2)=ROUND(D12,2),"PASS","FAIL") -> PASS
B13: Agent roster count | C13: 14 | D13: =COUNTA('Agent Roster'!B5:B18) -> 14 | E13: =IF(ROUND(C13,2)=ROUND(D13,2),"PASS","FAIL") -> PASS
B14: MCP server count | C14: 13 | D14: =COUNTA('MCP Integration'!B5:B17) -> 13 | E14: =IF(ROUND(C14,2)=ROUND(D14,2),"PASS","FAIL") -> PASS
B15: Score recompute matches | C15: =ROUND('Scoring Model'!E6*'Scoring Model'!C6+'Scoring Model'!E7*'Scoring Model'!C7+'Scoring Model'!E8*'Scoring Model'!C8+'Scoring Model'!E9*'Scoring Model'!C9+'Scoring Model'!E10*'Scoring Model'!C10+'Scoring Model'!E11*'Scoring Model'!C11,1) -> 46.5 | D15: ='Scoring Model'!F15 -> 46.5 | E15: =IF(ROUND(C15,2)=ROUND(D15,2),"PASS","FAIL") -> PASS
B16: Top risk score within 1-25 | C16: 1 | D16: =IF(MAX('Risk Register'!G5:G14)<=25,1,0) -> 1 | E16: =IF(ROUND(C16,2)=ROUND(D16,2),"PASS","FAIL") -> PASS
B17: Console screen count | C17: 10 | D17: =COUNTA('Console UI'!B12:B21) -> 10 | E17: =IF(ROUND(C17,2)=ROUND(D17,2),"PASS","FAIL") -> PASS
B18: Execution milestone count | C18: 12 | D18: =COUNTA('Exec Milestones'!B6:B17) -> 12 | E18: =IF(ROUND(C18,2)=ROUND(D18,2),"PASS","FAIL") -> PASS
B19: Locked decisions count | C19: 9 | D19: =COUNTA('Context Memory'!B6:B14) -> 9 | E19: =IF(ROUND(C19,2)=ROUND(D19,2),"PASS","FAIL") -> PASS
B21: Live formulas re-evaluate on any edit; bake step refreshes cached values for static viewers.

Sheet Sources
B2: Sources & Data Provenance
B4: # | C4: Data Point | D4: Source | E4: URL
B5: 1 | C5: 40% of enterprise apps with task-specific agents by end-2026; $234B spend at risk | D5: Gartner (Jul 2026) | E5: https://www.gartner.com/en/newsroom/press-releases/2026-07-01-gartner-says-us-dollars-234-billion-in-enterprise-application-software-spend-is-at-risk-from-agentic-artificial-intelligence
B6: 2 | C6: AI red-teaming market ~$2.3B (2026) to $6.2B (2030), ~28% CAGR | D6: Market.US | E6: https://market.us/report/ai-red-teaming-services-market/
B7: 3 | C7: LLM application top 10 risks (2025) — primary taxonomy | D7: OWASP GenAI Security Project | E7: https://genai.owasp.org/
B8: 4 | C8: Top 10 for agentic applications (2026) — agent-specific risks | D8: OWASP Agentic Security Initiative | E8: https://genai.owasp.org/agentic-top-10/
B9: 5 | C9: Adversarial ML threat taxonomy (ATLAS) | D9: MITRE ATLAS | E9: https://atlas.mitre.org/
B10: 6 | C10: Adversarial machine learning taxonomy and metrics | D10: NIST AI 100-2.5 | E10: https://csrc.nist.gov/pubs/ai/100/2/5/final
B11: 7 | C11: AI risk management framework + Generative AI profile | D11: NIST AI RMF | E11: https://www.nist.gov/itl/ai-risk-management-framework
B12: 8 | C12: AI robustness/cybersecurity evidence duties (Art 15, Annex I) | D12: EU AI Act (enforcement Aug 2026) | E12: https://artificialintelligenceact.eu/
B13: 9 | C13: AI management system certifiable controls | D13: ISO/IEC 42001 | E13: https://www.iso.org/standard/42001
B14: 10 | C14: AI red-team orchestration (multi-turn, memory, scoring) | D14: Microsoft PyRIT | E14: https://github.com/Azure/PyRIT
B15: 11 | C15: LLM vulnerability probes (encoding, policy, leak probes) | D15: NVIDIA Garak | E15: https://github.com/NVIDIA/garak
B16: 12 | C16: Red-team test suites + CI regression | D16: promptfoo | E16: https://www.promptfoo.dev/
... B19: 15 | C19: CSA agentic red-teaming guidance incl. tool misuse testing | D19: Cloud Security Alliance | E19: https://cloudsecurityalliance.org/
B21: Directional planning estimates prepared Sep 2026. Validate market figures before board or pricing use. Sensitive techniques (marked in Technique Catalog) execute only under signed ROAI with budget caps. Tools are anchor picks, not endorsements.
